{"lastUpdated":"2023-08-19T10:30:00.000+0100","twitterEnabled":0,"incidents":[{"loc":[50.21991,-5.268592],"id":"INCD-6789-l","region":"South West"},{"loc":[50.38373,-3.522953],"id":"INCD-6777-l","region":"South West"},{"loc":[50.43029,-3.674611],"id":"INCD-6794-l","region":"South West"},{"loc":[51.64828,-3.292099],"id":"INCD-4340-f","region":"South Wales"},{"loc":[51.68038,-4.781963],"id":"INCD-4336-f","region":"South Wales"},{"loc":[52.4799,-1.969021],"id":"INCD-5610-p","region":"West Midlands"},{"loc":[52.61,-1.927181],"id":"INCD-5215-m","region":"West Midlands"},{"loc":[52.09685,-1.873437],"id":"INCD-5200-m","region":"West Midlands"},{"loc":[52.337,-1.415777],"id":"INCD-12532-h","region":"East Midlands"},{"loc":[53.12823,-1.184674],"id":"INCD-12538-h","region":"East Midlands"},{"loc":[52.78936,-1.560801],"id":"INCD-12554-h","region":"East Midlands"},{"loc":[52.4785,-0.919316],"id":"INCD-12510-h","region":"East Midlands"},{"loc":[52.41546,-1.452605],"id":"INCD-12534-h","region":"East Midlands"},{"loc":[52.9023,-1.434555],"id":"INCD-12559-h","region":"East Midlands"},{"loc":[52.38497,-1.63473],"id":"INCD-12514-h","region":"East Midlands"},{"loc":[52.273,-1.39061],"id":"INCD-12562-h","region":"East Midlands"}],"updatePeriod":60000,"incidentStatus":200,"alertSummary":[{"id":8,"published":"Aug 18, 2023, 3:30:00 PM","flagAsNew":true,"isDefault":false}]}