{"incidents":"{\"lastUpdated\":1673236740000,\"incidents\":[{\"id\":\"INCD-41300-q\",\"loc\":[50.37825,-4.585009]},{\"id\":\"INCD-25496-g\",\"loc\":[51.52792,-3.6973]},{\"id\":\"INCD-42628-c\",\"loc\":[51.77826,-2.092878]},{\"id\":\"INCD-42625-c\",\"loc\":[52.51574,-1.835723]},{\"id\":\"INCD-31085-b\",\"loc\":[53.163,-2.203926]},{\"id\":\"INCD-53167-m\",\"loc\":[53.08339,-0.960157]},{\"id\":\"INCD-53174-m\",\"loc\":[52.67119,-0.2967243]},{\"id\":\"INCD-53177-m\",\"loc\":[52.95921,-1.232307]}]}","incidentStatus":200,"alertSummary":"[{\"flagAsNew\":true,\"id\":26,\"published\":1656920347000}]"}