{"lastUpdated":"2024-01-26T15:30:00.000+0000","twitterEnabled":0,"incidents":[{"loc":[51.03405,-4.210808],"id":"INCD-6888-t","region":"South West"},{"loc":[50.40127,-4.109225],"id":"INCD-28425-v","region":"South West"},{"loc":[50.19103,-5.410726],"id":"INCD-28418-v","region":"South West"},{"loc":[51.19173,-2.558264],"id":"INCD-4165-u","region":"South West"},{"loc":[50.84718,-4.297709],"id":"INCD-6874-t","region":"South West"},{"loc":[50.4945,-4.081497],"id":"INCD-16748-l","region":"South West"},{"loc":[51.48473,-3.157506],"id":"INCD-9558-e","region":"South Wales"},{"loc":[51.80772,-4.963903],"id":"INCD-9598-e","region":"South Wales"},{"loc":[52.52703,-1.660409],"id":"INCD-16214-p","region":"West Midlands"},{"loc":[52.69351,-2.401369],"id":"INCD-16219-p","region":"West Midlands"},{"loc":[51.89606,-2.2781],"id":"INCD-14021-m","region":"West Midlands"},{"loc":[52.61052,-2.48458],"id":"INCD-14001-m","region":"West Midlands"},{"loc":[52.65593,-1.879283],"id":"INCD-14023-m","region":"West Midlands"},{"loc":[52.47291,-1.932368],"id":"INCD-16234-p","region":"West Midlands"},{"loc":[53.18241,-1.872007],"id":"INCD-14004-m","region":"West Midlands"},{"loc":[52.94522,-2.133937],"id":"INCD-14028-m","region":"West Midlands"},{"loc":[52.47303,-2.053028],"id":"INCD-16181-p","region":"West Midlands"},{"loc":[51.88862,-2.116702],"id":"INCD-16262-p","region":"West Midlands"},{"loc":[52.5242,-1.816221],"id":"INCD-16287-p","region":"West Midlands"},{"loc":[52.77003,-1.233192],"id":"INCD-33026-h","region":"East Midlands"},{"loc":[53.08588,-0.959724],"id":"INCD-32971-h","region":"East Midlands"},{"loc":[53.15432,-1.19333],"id":"INCD-33062-h","region":"East Midlands"},{"loc":[52.78037,-1.574605],"id":"INCD-32919-h","region":"East Midlands"},{"loc":[53.0997,-1.249106],"id":"INCD-33063-h","region":"East Midlands"},{"loc":[52.41696,-1.558406],"id":"INCD-32998-h","region":"East Midlands"}],"updatePeriod":60000,"incidentStatus":200,"alertSummary":[{"id":6,"published":"Mar 15, 2021, 8:00:00 AM","flagAsNew":false,"isDefault":true}]}