{"lastUpdated":"2023-10-24T19:06:00.000+0100","twitterEnabled":0,"incidents":[{"loc":[51.11525,-2.657232],"id":"INCD-10685-l","region":"South West"},{"loc":[50.107,-5.272741],"id":"INCD-25373-v","region":"South West"},{"loc":[50.72384,-3.53581],"id":"INCD-10684-l","region":"South West"},{"loc":[50.79939,-3.89804],"id":"INCD-4071-t","region":"South West"},{"loc":[50.24148,-3.81123],"id":"INCD-10679-l","region":"South West"},{"loc":[50.42701,-3.832437],"id":"INCD-25381-v","region":"South West"},{"loc":[50.43497,-3.569024],"id":"INCD-4036-t","region":"South West"},{"loc":[51.59751,-3.342923],"id":"INCD-1186-j","region":"South Wales"},{"loc":[51.61554,-3.4365],"id":"INCD-1185-j","region":"South Wales"},{"loc":[52.51172,-1.76858],"id":"INCD-9846-p","region":"West Midlands"},{"loc":[52.35957,-1.873511],"id":"INCD-9865-p","region":"West Midlands"},{"loc":[51.8731,-2.137317],"id":"INCD-8936-m","region":"West Midlands"},{"loc":[53.10335,-2.023917],"id":"INCD-350403-f","region":"West Midlands"},{"loc":[52.97437,-2.133551],"id":"INCD-8927-m","region":"West Midlands"},{"loc":[52.24871,-2.246442],"id":"INCD-8931-m","region":"West Midlands"},{"loc":[53.02394,-1.414702],"id":"INCD-20534-h","region":"East Midlands"},{"loc":[52.9255,-1.47638],"id":"INCD-20045-h","region":"East Midlands"},{"loc":[52.4062,-0.730876],"id":"INCD-20618-h","region":"East Midlands"},{"loc":[52.4936,-0.500493],"id":"INCD-20624-h","region":"East Midlands"},{"loc":[52.00517,-0.74847],"id":"INCD-20581-h","region":"East Midlands"},{"loc":[53.23073,-1.41947],"id":"INCD-19852-h","region":"East Midlands"},{"loc":[53.20381,-1.213977],"id":"INCD-20584-h","region":"East Midlands"},{"loc":[53.2258,-1.425362],"id":"INCD-20023-h","region":"East Midlands"},{"loc":[53.30073,-1.3171],"id":"INCD-20482-h","region":"East Midlands"}],"updatePeriod":60000,"incidentStatus":200,"alertSummary":[{"id":8,"published":"Oct 20, 2023, 11:30:00 AM","flagAsNew":true,"isDefault":false}]}