{"lastUpdated":"2023-12-06T12:47:00.000+0000","twitterEnabled":0,"incidents":[{"loc":[51.489,-2.612845],"id":"INCD-3354-u","region":"South West"},{"loc":[51.46409,-2.55004],"id":"INCD-13428-l","region":"South West"},{"loc":[51.28314,-2.447662],"id":"INCD-13419-l","region":"South West"},{"loc":[51.10934,-2.932113],"id":"INCD-5447-t","region":"South West"},{"loc":[51.36532,-2.919203],"id":"INCD-13416-l","region":"South West"},{"loc":[51.7286,-5.054325],"id":"INCD-7852-f","region":"South Wales"},{"loc":[51.57033,-4.036975],"id":"INCD-7672-e","region":"South Wales"},{"loc":[51.8873,-5.096709],"id":"INCD-7858-f","region":"South Wales"},{"loc":[51.97857,-4.971564],"id":"INCD-7857-f","region":"South Wales"},{"loc":[51.74678,-3.620922],"id":"INCD-7697-e","region":"South Wales"},{"loc":[51.6044,-3.441419],"id":"INCD-7669-e","region":"South Wales"},{"loc":[52.46126,-1.6531],"id":"INCD-12594-p","region":"West Midlands"},{"loc":[52.46031,-2.150295],"id":"INCD-12599-p","region":"West Midlands"},{"loc":[52.21557,-2.178813],"id":"INCD-4752-l","region":"West Midlands"},{"loc":[51.70494,-2.185443],"id":"INCD-350921-f","region":"West Midlands"},{"loc":[52.67152,-2.43276],"id":"INCD-12610-p","region":"West Midlands"},{"loc":[52.65897,-2.138913],"id":"INCD-12585-p","region":"West Midlands"},{"loc":[53.07653,-1.170798],"id":"INCD-25806-h","region":"East Midlands"},{"loc":[52.99148,-1.31999],"id":"INCD-25929-h","region":"East Midlands"},{"loc":[52.47149,-1.492837],"id":"INCD-25946-h","region":"East Midlands"},{"loc":[52.35374,-1.386021],"id":"INCD-25938-h","region":"East Midlands"},{"loc":[52.86979,-1.684229],"id":"INCD-25949-h","region":"East Midlands"},{"loc":[52.7492,-1.473989],"id":"INCD-25933-h","region":"East Midlands"},{"loc":[52.36883,-1.265683],"id":"INCD-25928-h","region":"East Midlands"},{"loc":[52.34005,-1.559877],"id":"INCD-25956-h","region":"East Midlands"},{"loc":[53.15648,-1.367366],"id":"INCD-10730-t","region":"East Midlands"},{"loc":[52.35241,-1.271123],"id":"INCD-25883-h","region":"East Midlands"},{"loc":[52.52899,-1.154391],"id":"INCD-25886-h","region":"East Midlands"},{"loc":[53.26953,-1.422991],"id":"INCD-25962-h","region":"East Midlands"}],"updatePeriod":60000,"incidentStatus":200,"alertSummary":[{"id":6,"published":"Mar 15, 2021, 8:00:00 AM","flagAsNew":false,"isDefault":true}]}