{"lastUpdated":"2023-04-29T20:30:00.000+0100","twitterEnabled":0,"incidents":[{"loc":[51.8223,-2.51012],"id":"INCD-36597-b","region":"West Midlands"},{"loc":[52.08323,-2.64016],"id":"INCD-348041-f","region":"West Midlands"},{"loc":[52.69117,-1.701615],"id":"INCD-348035-f","region":"West Midlands"},{"loc":[52.34932,-1.573086],"id":"INCD-65032-m","region":"East Midlands"},{"loc":[53.01283,-1.16482],"id":"INCD-28812-q","region":"East Midlands"},{"loc":[52.1839,-0.801206],"id":"INCD-28777-q","region":"East Midlands"},{"loc":[52.98383,-1.098678],"id":"INCD-28810-q","region":"East Midlands"}],"updatePeriod":60000,"incidentStatus":200,"alertSummary":[{"id":26,"published":"Jul 4, 2022, 8:39:07 AM","flagAsNew":true,"isDefault":false}]}