{"lastUpdated":"2024-02-11T21:30:00.000+0000","twitterEnabled":0,"incidents":[{"loc":[50.92695,-2.910064],"id":"INCD-17610-l","region":"South West"},{"loc":[51.4174,-2.615325],"id":"INCD-17607-l","region":"South West"},{"loc":[51.74011,-2.238347],"id":"INCD-14694-m","region":"West Midlands"},{"loc":[51.74011,-2.238347],"id":"INCD-14695-m","region":"West Midlands"},{"loc":[52.4119,-1.58565],"id":"INCD-34964-h","region":"East Midlands"},{"loc":[52.50185,-1.575573],"id":"INCD-34957-h","region":"East Midlands"},{"loc":[52.43683,-1.646202],"id":"INCD-34951-h","region":"East Midlands"}],"updatePeriod":60000,"incidentStatus":200,"alertSummary":[{"id":6,"published":"Mar 15, 2021, 8:00:00 AM","flagAsNew":false,"isDefault":true}]}