{"lastUpdated":"2024-03-14T21:01:00.000+0000","twitterEnabled":0,"incidents":[{"loc":[50.428,-3.825941],"id":"INCD-19387-l","region":"South West"},{"loc":[52.58706,-2.133549],"id":"INCD-19496-p","region":"West Midlands"},{"loc":[52.69799,-1.817758],"id":"INCD-16096-m","region":"West Midlands"},{"loc":[52.40837,-1.582042],"id":"INCD-38472-h","region":"East Midlands"},{"loc":[52.37232,-1.2553],"id":"INCD-38386-h","region":"East Midlands"},{"loc":[53.02953,-1.204131],"id":"INCD-38463-h","region":"East Midlands"},{"loc":[52.30177,-0.68796],"id":"INCD-38471-h","region":"East Midlands"}],"updatePeriod":60000,"incidentStatus":200,"alertSummary":[{"id":6,"published":"Mar 15, 2021, 8:00:00 AM","flagAsNew":false,"isDefault":true}]}