{"incidents":"{\"lastUpdated\":1673537940000,\"incidents\":[{\"id\":\"INCD-41546-q\",\"loc\":[50.65605,-3.65538]},{\"id\":\"INCD-17584-v\",\"loc\":[50.38767,-4.047214]},{\"id\":\"INCD-41548-q\",\"loc\":[50.62658,-4.713431]},{\"id\":\"INCD-41549-q\",\"loc\":[51.55002,-2.569333]},{\"id\":\"INCD-11424-r\",\"loc\":[51.45336,-2.571439]},{\"id\":\"INCD-41553-q\",\"loc\":[51.14794,-3.125669]},{\"id\":\"INCD-17531-v\",\"loc\":[50.28354,-3.777384]},{\"id\":\"INCD-25695-g\",\"loc\":[51.60676,-4.17634]},{\"id\":\"INCD-25686-g\",\"loc\":[51.55989,-3.238236]},{\"id\":\"INCD-24043-h\",\"loc\":[51.68891,-4.212646]},{\"id\":\"INCD-25641-g\",\"loc\":[51.42906,-3.171288]},{\"id\":\"INCD-3954-t\",\"loc\":[51.71533,-2.930959]},{\"id\":\"INCD-25593-g\",\"loc\":[51.54049,-3.45776]},{\"id\":\"INCD-42982-c\",\"loc\":[52.55755,-1.789635]},{\"id\":\"INCD-42898-c\",\"loc\":[52.41813,-1.851995]},{\"id\":\"INCD-42966-c\",\"loc\":[51.69778,-2.228676]},{\"id\":\"INCD-31293-b\",\"loc\":[52.98733,-2.292219]},{\"id\":\"INCD-42958-c\",\"loc\":[52.14913,-2.063938]},{\"id\":\"INCD-31256-b\",\"loc\":[52.98816,-2.043128]},{\"id\":\"INCD-31277-b\",\"loc\":[52.05453,-1.855997]},{\"id\":\"INCD-31278-b\",\"loc\":[52.58463,-2.259186]},{\"id\":\"INCD-31291-b\",\"loc\":[52.0741,-2.714601]},{\"id\":\"INCD-53637-m\",\"loc\":[52.621,-0.8155272]},{\"id\":\"INCD-53575-m\",\"loc\":[52.59621,-1.13357]},{\"id\":\"INCD-53632-m\",\"loc\":[52.97007,-1.16411]},{\"id\":\"INCD-53546-m\",\"loc\":[52.69661,-1.084716]},{\"id\":\"INCD-53589-m\",\"loc\":[52.57201,-1.409537]},{\"id\":\"INCD-53633-m\",\"loc\":[53.1177,-1.432346]},{\"id\":\"INCD-53554-m\",\"loc\":[52.9538,-1.497099]},{\"id\":\"INCD-53562-m\",\"loc\":[52.28269,-1.623712]},{\"id\":\"INCD-2561-u\",\"loc\":[52.27667,-1.695508]},{\"id\":\"INCD-53558-m\",\"loc\":[52.78552,-1.578587]}]}","incidentStatus":200,"alertSummary":"[{\"flagAsNew\":true,\"id\":26,\"published\":1656920347000}]"}