{"lastUpdated":"2023-03-31T06:30:00.000+0100","twitterEnabled":0,"incidents":[{"loc":[50.50831,-4.07044],"id":"INCD-45388-q","region":"South West"},{"loc":[50.22587,-5.205153],"id":"INCD-45387-q","region":"South West"},{"loc":[50.72944,-2.759116],"id":"INCD-45375-q","region":"South West"},{"loc":[50.82651,-4.506746],"id":"INCD-45383-q","region":"South West"},{"loc":[51.99031,-1.704166],"id":"INCD-48115-c","region":"West Midlands"},{"loc":[53.03937,-1.20571],"id":"INCD-62131-m","region":"East Midlands"},{"loc":[52.77144,-1.210089],"id":"INCD-62097-m","region":"East Midlands"},{"loc":[53.3061,-1.106329],"id":"INCD-62125-m","region":"East Midlands"},{"loc":[53.25871,-1.369367],"id":"INCD-62117-m","region":"East Midlands"}],"updatePeriod":60000,"incidentStatus":200,"alertSummary":[{"id":26,"published":"Jul 4, 2022, 8:39:07 AM","flagAsNew":true,"isDefault":false}]}