{"lastUpdated":"2024-01-08T13:30:00.000+0000","twitterEnabled":0,"incidents":[{"loc":[50.09595,-5.273888],"id":"INCD-27840-v","region":"South West"},{"loc":[51.3751,-2.388045],"id":"INCD-15588-l","region":"South West"},{"loc":[50.25494,-3.667009],"id":"INCD-27825-v","region":"South West"},{"loc":[50.5374,-4.613432],"id":"INCD-27823-v","region":"South West"},{"loc":[53.20194,0.347048],"id":"INCD-30495-h","region":"East Midlands"},{"loc":[52.9568,-1.321085],"id":"INCD-30488-h","region":"East Midlands"},{"loc":[53.22344,0.29961],"id":"INCD-30454-h","region":"East Midlands"},{"loc":[52.2917,-0.69789],"id":"INCD-30415-h","region":"East Midlands"},{"loc":[52.23984,-0.88678],"id":"INCD-30480-h","region":"East Midlands"},{"loc":[52.90818,-1.506757],"id":"INCD-30493-h","region":"East Midlands"},{"loc":[52.02522,-0.673111],"id":"INCD-30476-h","region":"East Midlands"},{"loc":[53.15584,-1.199808],"id":"INCD-29843-h","region":"East Midlands"},{"loc":[53.3079,-1.360973],"id":"INCD-30489-h","region":"East Midlands"},{"loc":[52.92294,-1.209388],"id":"INCD-30486-h","region":"East Midlands"}],"updatePeriod":60000,"incidentStatus":200,"alertSummary":[{"id":6,"published":"Mar 15, 2021, 8:00:00 AM","flagAsNew":false,"isDefault":true}]}