{"lastUpdated":"2023-08-01T10:30:00.000+0100","twitterEnabled":0,"incidents":[{"loc":[50.48486,-3.524906],"id":"INCD-23005-v","region":"South West"},{"loc":[51.06112,-3.995284],"id":"INCD-1900-t","region":"South West"},{"loc":[50.46006,-3.594918],"id":"INCD-23003-v","region":"South West"},{"loc":[50.68142,-3.301237],"id":"INCD-1891-t","region":"South West"},{"loc":[50.43342,-3.688479],"id":"INCD-5269-l","region":"South West"},{"loc":[50.72513,-3.561002],"id":"INCD-1901-t","region":"South West"},{"loc":[51.6408,-2.669284],"id":"INCD-611-j","region":"South Wales"},{"loc":[51.6902,-4.895814],"id":"INCD-3056-e","region":"South Wales"},{"loc":[51.93499,-2.57959],"id":"INCD-4527-p","region":"West Midlands"},{"loc":[53.0395,-2.173752],"id":"INCD-4063-m","region":"West Midlands"},{"loc":[51.7142,-2.537769],"id":"INCD-4069-m","region":"West Midlands"},{"loc":[53.30633,-0.943989],"id":"INCD-10534-h","region":"East Midlands"},{"loc":[52.77287,-0.89962],"id":"INCD-10546-h","region":"East Midlands"},{"loc":[52.07675,-0.842601],"id":"INCD-10558-h","region":"East Midlands"},{"loc":[52.91695,-0.603973],"id":"INCD-10564-h","region":"East Midlands"},{"loc":[52.97772,-0.376295],"id":"INCD-10473-h","region":"East Midlands"}],"updatePeriod":60000,"incidentStatus":200,"alertSummary":[{"id":6,"published":"Mar 15, 2021, 8:00:00 AM","flagAsNew":false,"isDefault":true}]}