{"lastUpdated":"2023-12-07T19:30:00.000+0000","twitterEnabled":0,"incidents":[{"loc":[50.51755,-3.759316],"id":"INCD-27053-v","region":"South West"},{"loc":[50.26494,-5.035229],"id":"INCD-13502-l","region":"South West"},{"loc":[50.54661,-4.135199],"id":"INCD-27063-v","region":"South West"},{"loc":[50.43399,-4.103681],"id":"INCD-13467-l","region":"South West"},{"loc":[50.41333,-4.155775],"id":"INCD-27062-v","region":"South West"},{"loc":[51.11908,-2.989032],"id":"INCD-13500-l","region":"South West"},{"loc":[51.38566,-2.82068],"id":"INCD-3349-u","region":"South West"},{"loc":[50.41982,-5.049645],"id":"INCD-13486-l","region":"South West"},{"loc":[51.12784,-3.003652],"id":"INCD-13497-l","region":"South West"},{"loc":[51.20956,-2.65803],"id":"INCD-13498-l","region":"South West"},{"loc":[50.76664,-3.358819],"id":"INCD-5495-t","region":"South West"},{"loc":[51.68435,-4.119705],"id":"INCD-7767-e","region":"South Wales"},{"loc":[51.51695,-3.573804],"id":"INCD-7765-e","region":"South Wales"},{"loc":[52.40857,-1.873533],"id":"INCD-12640-p","region":"West Midlands"},{"loc":[51.68172,-2.158707],"id":"INCD-350965-f","region":"West Midlands"},{"loc":[52.40393,-2.023312],"id":"INCD-12644-p","region":"West Midlands"},{"loc":[52.14875,-2.676643],"id":"INCD-11393-m","region":"West Midlands"},{"loc":[51.9117,-2.059121],"id":"INCD-12662-p","region":"West Midlands"},{"loc":[52.67019,-2.371076],"id":"INCD-11337-m","region":"West Midlands"},{"loc":[52.44075,-1.943922],"id":"INCD-12682-p","region":"West Midlands"},{"loc":[52.99877,-2.117043],"id":"INCD-11390-m","region":"West Midlands"},{"loc":[52.49171,-0.903527],"id":"INCD-26123-h","region":"East Midlands"},{"loc":[53.17397,-1.193068],"id":"INCD-26141-h","region":"East Midlands"},{"loc":[52.37242,-1.261717],"id":"INCD-26168-h","region":"East Midlands"},{"loc":[52.64478,-1.08581],"id":"INCD-26115-h","region":"East Midlands"},{"loc":[52.75721,-0.321526],"id":"INCD-26152-h","region":"East Midlands"},{"loc":[53.00276,-1.118953],"id":"INCD-26153-h","region":"East Midlands"},{"loc":[52.35374,-1.386021],"id":"INCD-26106-h","region":"East Midlands"},{"loc":[52.54271,-1.379997],"id":"INCD-26170-h","region":"East Midlands"},{"loc":[52.82637,-1.638269],"id":"INCD-26107-h","region":"East Midlands"},{"loc":[52.90823,-0.044687],"id":"INCD-26124-h","region":"East Midlands"},{"loc":[53.18223,-1.12155],"id":"INCD-26135-h","region":"East Midlands"},{"loc":[52.53733,-1.373511],"id":"INCD-26154-h","region":"East Midlands"},{"loc":[52.33738,-0.60044],"id":"INCD-26035-h","region":"East Midlands"}],"updatePeriod":60000,"incidentStatus":200,"alertSummary":[{"id":6,"published":"Mar 15, 2021, 8:00:00 AM","flagAsNew":false,"isDefault":true}]}