{"lastUpdated":"2023-04-18T00:02:00.000+0100","twitterEnabled":0,"incidents":[{"loc":[50.3568,-4.117516],"id":"INCD-46529-q","region":"South West"},{"loc":[50.77595,-3.679922],"id":"INCD-46535-q","region":"South West"},{"loc":[50.28881,-5.236961],"id":"INCD-46528-q","region":"South West"},{"loc":[50.37028,-4.174243],"id":"INCD-46533-q","region":"South West"},{"loc":[52.53359,-1.788807],"id":"INCD-347909-f","region":"West Midlands"},{"loc":[52.65641,-2.084385],"id":"INCD-49074-c","region":"West Midlands"},{"loc":[51.89819,-2.04784],"id":"INCD-49029-c","region":"West Midlands"},{"loc":[53.22883,-1.4671],"id":"INCD-63820-m","region":"East Midlands"},{"loc":[52.60243,-1.137592],"id":"INCD-63838-m","region":"East Midlands"},{"loc":[53.00044,-1.599745],"id":"INCD-63827-m","region":"East Midlands"}],"updatePeriod":60000,"incidentStatus":200,"alertSummary":[{"id":26,"published":"Jul 4, 2022, 8:39:07 AM","flagAsNew":true,"isDefault":false}]}