{"lastUpdated":"2023-12-07T08:07:00.000+0000","twitterEnabled":0,"incidents":[{"loc":[51.6044,-3.441419],"id":"INCD-7886-f","region":"South Wales"},{"loc":[51.80655,-4.93369],"id":"INCD-7872-f","region":"South Wales"},{"loc":[52.20555,-2.215517],"id":"INCD-11333-m","region":"West Midlands"},{"loc":[52.71855,-2.743864],"id":"INCD-11323-m","region":"West Midlands"},{"loc":[52.08851,-1.390746],"id":"INCD-350941-f","region":"West Midlands"},{"loc":[51.8584,-2.048582],"id":"INCD-11325-m","region":"West Midlands"},{"loc":[53.03986,-2.295736],"id":"INCD-11332-m","region":"West Midlands"},{"loc":[52.21557,-2.178813],"id":"INCD-4752-l","region":"West Midlands"},{"loc":[52.81188,-0.676616],"id":"INCD-26059-h","region":"East Midlands"},{"loc":[52.74798,-1.485797],"id":"INCD-26054-h","region":"East Midlands"},{"loc":[52.33738,-0.60044],"id":"INCD-26035-h","region":"East Midlands"},{"loc":[52.73616,-1.109437],"id":"INCD-26056-h","region":"East Midlands"},{"loc":[53.09081,-0.798498],"id":"INCD-26053-h","region":"East Midlands"}],"updatePeriod":60000,"incidentStatus":200,"alertSummary":[{"id":6,"published":"Mar 15, 2021, 8:00:00 AM","flagAsNew":false,"isDefault":true}]}