{"lastUpdated":"2023-01-30T13:36:00.000+0000","incidents":[{"loc":[51.00135,-3.112283],"id":"INCD-42526-q","region":"South West"},{"loc":[50.45121,-4.4655],"id":"INCD-18038-v","region":"South West"},{"loc":[50.80941,-2.749768],"id":"INCD-18261-s","region":"South West"},{"loc":[51.1588,-2.706641],"id":"INCD-18246-s","region":"South West"},{"loc":[51.80972,-3.121675],"id":"INCD-24605-h","region":"South Wales"},{"loc":[51.5877,-3.005355],"id":"INCD-4064-t","region":"South Wales"},{"loc":[51.70169,-2.468135],"id":"INCD-32260-b","region":"West Midlands"},{"loc":[52.70825,-2.534742],"id":"INCD-32266-b","region":"West Midlands"},{"loc":[52.76556,-2.842792],"id":"INCD-32253-b","region":"West Midlands"},{"loc":[53.10502,-2.020498],"id":"INCD-32236-b","region":"West Midlands"},{"loc":[52.5804,-2.15084],"id":"INCD-32262-b","region":"West Midlands"},{"loc":[52.4337,-1.893656],"id":"INCD-32246-b","region":"West Midlands"},{"loc":[51.84995,-2.713207],"id":"INCD-44109-c","region":"West Midlands"},{"loc":[52.1295,-2.074895],"id":"INCD-44126-c","region":"West Midlands"},{"loc":[52.8366,-1.554609],"id":"INCD-55516-m","region":"East Midlands"},{"loc":[53.07356,-1.405165],"id":"INCD-55469-m","region":"East Midlands"},{"loc":[52.29408,-1.525553],"id":"INCD-55458-m","region":"East Midlands"},{"loc":[52.99646,-1.310242],"id":"INCD-55489-m","region":"East Midlands"}],"updatePeriod":60000,"incidentStatus":200,"alertSummary":[{"id":26,"published":"Jul 4, 2022, 8:39:07 AM","flagAsNew":true,"isDefault":false}]}