{"lastUpdated":"2023-09-04T22:01:00.000+0100","twitterEnabled":0,"incidents":[{"loc":[50.54906,-3.586219],"id":"INCD-7702-l","region":"South West"},{"loc":[50.88999,-2.789732],"id":"INCD-7693-l","region":"South West"},{"loc":[50.77595,-3.679922],"id":"INCD-7701-l","region":"South West"},{"loc":[50.26918,-5.01011],"id":"INCD-23968-v","region":"South West"},{"loc":[50.46329,-3.506205],"id":"INCD-7674-l","region":"South West"},{"loc":[51.4011,-3.290223],"id":"INCD-4121-e","region":"South Wales"},{"loc":[52.6154,-2.262825],"id":"INCD-6340-p","region":"West Midlands"},{"loc":[51.90642,-2.71907],"id":"INCD-6354-p","region":"West Midlands"},{"loc":[52.38656,-2.16706],"id":"INCD-6367-p","region":"West Midlands"},{"loc":[52.38495,-2.307792],"id":"INCD-6306-m","region":"West Midlands"},{"loc":[53.25435,-1.746652],"id":"INCD-14168-h","region":"East Midlands"},{"loc":[52.89798,-1.27491],"id":"INCD-14207-h","region":"East Midlands"},{"loc":[52.11622,-0.798963],"id":"INCD-14172-h","region":"East Midlands"},{"loc":[53.10348,-1.624719],"id":"INCD-14197-h","region":"East Midlands"},{"loc":[52.72242,-1.21238],"id":"INCD-14204-h","region":"East Midlands"},{"loc":[52.58205,-1.63],"id":"INCD-14169-h","region":"East Midlands"},{"loc":[53.08907,-0.803563],"id":"INCD-14091-h","region":"East Midlands"},{"loc":[52.88326,-1.310865],"id":"INCD-14206-h","region":"East Midlands"}],"updatePeriod":60000,"incidentStatus":200,"alertSummary":[{"id":6,"published":"Mar 15, 2021, 8:00:00 AM","flagAsNew":false,"isDefault":true}]}