{"lastUpdated":"2024-03-08T23:30:00.000+0000","twitterEnabled":0,"incidents":[{"loc":[51.15059,-2.712964],"id":"INCD-19108-l","region":"South West"},{"loc":[51.45735,-2.580873],"id":"INCD-19084-l","region":"South West"},{"loc":[50.74512,-2.927086],"id":"INCD-19104-l","region":"South West"},{"loc":[50.42667,-4.119351],"id":"INCD-19107-l","region":"South West"},{"loc":[53.07908,-2.234966],"id":"INCD-15833-m","region":"West Midlands"},{"loc":[52.65509,-2.48744],"id":"INCD-15831-m","region":"West Midlands"},{"loc":[52.9776,-1.889842],"id":"INCD-15820-m","region":"West Midlands"},{"loc":[52.59767,-1.922241],"id":"INCD-5880-l","region":"West Midlands"},{"loc":[52.53471,-1.99832],"id":"INCD-15830-m","region":"West Midlands"},{"loc":[52.28988,-0.58902],"id":"INCD-11776-t","region":"East Midlands"},{"loc":[52.65204,-0.478417],"id":"INCD-11753-t","region":"East Midlands"},{"loc":[52.84455,-1.648437],"id":"INCD-11784-t","region":"East Midlands"}],"updatePeriod":60000,"incidentStatus":200,"alertSummary":[{"id":6,"published":"Mar 15, 2021, 8:00:00 AM","flagAsNew":false,"isDefault":true}]}