{"lastUpdated":"2023-07-02T17:36:00.000+0100","twitterEnabled":0,"incidents":[{"loc":[51.2906,-2.478338],"id":"INCD-3172-l","region":"South West"},{"loc":[50.43923,-3.563306],"id":"INCD-3187-l","region":"South West"},{"loc":[51.50932,-2.573133],"id":"INCD-3191-l","region":"South West"},{"loc":[51.22284,-2.981216],"id":"INCD-3181-l","region":"South West"},{"loc":[50.85112,-3.224313],"id":"INCD-3197-l","region":"South West"},{"loc":[51.29167,-2.448261],"id":"INCD-3196-l","region":"South West"},{"loc":[50.28433,-4.98345],"id":"INCD-3178-l","region":"South West"},{"loc":[51.061,-3.035313],"id":"INCD-3192-l","region":"South West"},{"loc":[51.58244,-4.093954],"id":"INCD-2592-f","region":"South Wales"},{"loc":[51.83881,-3.01386],"id":"INCD-2589-f","region":"South Wales"},{"loc":[52.12568,-2.318067],"id":"INCD-2373-p","region":"West Midlands"},{"loc":[52.62706,-2.051176],"id":"INCD-2359-p","region":"West Midlands"},{"loc":[52.07462,-1.357581],"id":"INCD-2360-p","region":"West Midlands"},{"loc":[52.2487,-2.190635],"id":"INCD-2185-m","region":"West Midlands"},{"loc":[52.66131,-2.037998],"id":"INCD-2176-m","region":"West Midlands"},{"loc":[51.92437,-2.482111],"id":"INCD-2399-p","region":"West Midlands"},{"loc":[52.49121,-1.76733],"id":"INCD-2388-p","region":"West Midlands"},{"loc":[52.88458,-1.445961],"id":"INCD-6702-h","region":"East Midlands"},{"loc":[52.98444,-1.128069],"id":"INCD-6687-h","region":"East Midlands"},{"loc":[52.75923,-1.235042],"id":"INCD-6716-h","region":"East Midlands"},{"loc":[53.1685,0.104636],"id":"INCD-6724-h","region":"East Midlands"},{"loc":[53.1021,-1.565017],"id":"INCD-6731-h","region":"East Midlands"},{"loc":[53.07953,-1.529806],"id":"INCD-6729-h","region":"East Midlands"},{"loc":[53.21676,-0.604699],"id":"INCD-6697-h","region":"East Midlands"},{"loc":[51.99587,-0.97598],"id":"INCD-6730-h","region":"East Midlands"}],"updatePeriod":60000,"incidentStatus":200,"alertSummary":[{"id":6,"published":"Mar 15, 2021, 8:00:00 AM","flagAsNew":false,"isDefault":true}]}