{"lastUpdated":"2023-11-04T17:01:00.000+0000","twitterEnabled":0,"incidents":[{"loc":[50.23088,-5.24533],"id":"INCD-11693-l","region":"South West"},{"loc":[50.55531,-3.501555],"id":"INCD-11694-l","region":"South West"},{"loc":[50.74512,-2.927086],"id":"INCD-11659-l","region":"South West"},{"loc":[50.69887,-3.539725],"id":"INCD-11669-l","region":"South West"},{"loc":[50.1763,-5.420673],"id":"INCD-11686-l","region":"South West"},{"loc":[50.38103,-5.11568],"id":"INCD-11602-l","region":"South West"},{"loc":[51.22,-2.4296],"id":"INCD-11681-l","region":"South West"},{"loc":[50.4733,-4.710643],"id":"INCD-11673-l","region":"South West"},{"loc":[51.6679,-3.214486],"id":"INCD-6915-f","region":"South Wales"},{"loc":[52.51034,-2.117491],"id":"INCD-10545-p","region":"West Midlands"},{"loc":[52.93025,-1.525028],"id":"INCD-22104-h","region":"East Midlands"},{"loc":[52.73568,-1.392548],"id":"INCD-22115-h","region":"East Midlands"},{"loc":[53.29443,-1.095861],"id":"INCD-22091-h","region":"East Midlands"}],"updatePeriod":60000,"incidentStatus":200,"alertSummary":[{"id":6,"published":"Mar 15, 2021, 8:00:00 AM","flagAsNew":false,"isDefault":true}]}