{"lastUpdated":"2023-08-13T21:02:00.000+0100","twitterEnabled":0,"incidents":[{"loc":[50.5867,-4.107077],"id":"INCD-6396-l","region":"South West"},{"loc":[50.3875,-4.136625],"id":"INCD-6397-l","region":"South West"},{"loc":[50.19775,-5.147604],"id":"INCD-6374-l","region":"South West"},{"loc":[51.16496,-2.57178],"id":"INCD-6390-l","region":"South West"},{"loc":[50.61944,-3.416856],"id":"INCD-6391-l","region":"South West"},{"loc":[50.385,-4.02591],"id":"INCD-6384-l","region":"South West"},{"loc":[51.69458,-2.0594],"id":"INCD-5200-p","region":"West Midlands"},{"loc":[52.06961,-1.366931],"id":"INCD-5203-p","region":"West Midlands"},{"loc":[51.46163,-2.324179],"id":"INCD-5199-p","region":"West Midlands"},{"loc":[52.90196,-2.045704],"id":"INCD-5202-p","region":"West Midlands"},{"loc":[52.21538,-1.43119],"id":"INCD-11882-h","region":"East Midlands"},{"loc":[53.3118,-1.134412],"id":"INCD-11874-h","region":"East Midlands"},{"loc":[52.76433,-0.869719],"id":"INCD-11885-h","region":"East Midlands"}],"updatePeriod":60000,"incidentStatus":200,"alertSummary":[{"id":6,"published":"Mar 15, 2021, 8:00:00 AM","flagAsNew":false,"isDefault":true}]}