{"lastUpdated":"2023-10-22T08:01:00.000+0100","twitterEnabled":0,"incidents":[{"loc":[51.48226,-3.147478],"id":"INCD-6576-f","region":"South Wales"},{"loc":[52.46556,-1.778328],"id":"INCD-9634-p","region":"West Midlands"},{"loc":[52.9255,-1.47638],"id":"INCD-19970-h","region":"East Midlands"},{"loc":[52.89996,-1.257349],"id":"INCD-20092-h","region":"East Midlands"},{"loc":[52.68004,-1.124852],"id":"INCD-20008-h","region":"East Midlands"},{"loc":[52.71359,-1.058707],"id":"INCD-20147-h","region":"East Midlands"},{"loc":[52.44391,-1.4726],"id":"INCD-20151-h","region":"East Midlands"},{"loc":[53.23073,-1.41947],"id":"INCD-19852-h","region":"East Midlands"},{"loc":[53.2258,-1.425362],"id":"INCD-20023-h","region":"East Midlands"},{"loc":[53.02155,-1.327523],"id":"INCD-19916-h","region":"East Midlands"},{"loc":[52.9255,-1.47638],"id":"INCD-20045-h","region":"East Midlands"},{"loc":[53.33036,-1.657417],"id":"INCD-19982-h","region":"East Midlands"}],"updatePeriod":60000,"incidentStatus":200,"alertSummary":[{"id":8,"published":"Oct 20, 2023, 11:30:00 AM","flagAsNew":true,"isDefault":false}]}