{"lastUpdated":"2023-12-23T06:30:00.000+0000","twitterEnabled":0,"incidents":[{"loc":[50.38612,-3.91705],"id":"INCD-14252-l","region":"South West"},{"loc":[51.56701,-3.004754],"id":"INCD-8403-f","region":"South Wales"},{"loc":[52.60504,-2.05452],"id":"INCD-12221-m","region":"West Midlands"},{"loc":[53.1177,-1.432346],"id":"INCD-28565-h","region":"East Midlands"},{"loc":[52.69778,-0.051916],"id":"INCD-28566-h","region":"East Midlands"},{"loc":[52.71895,-0.780003],"id":"INCD-28487-h","region":"East Midlands"},{"loc":[52.58205,-1.63],"id":"INCD-28556-h","region":"East Midlands"}],"updatePeriod":60000,"incidentStatus":200,"alertSummary":[{"id":6,"published":"Mar 15, 2021, 8:00:00 AM","flagAsNew":false,"isDefault":true}]}