{"lastUpdated":"2023-04-12T14:30:00.000+0100","twitterEnabled":0,"incidents":[{"loc":[51.48149,-2.442129],"id":"INCD-46102-q","region":"South West"},{"loc":[50.08318,-5.687785],"id":"INCD-19938-v","region":"South West"},{"loc":[50.53535,-4.722458],"id":"INCD-46094-q","region":"South West"},{"loc":[50.28487,-3.779834],"id":"INCD-46118-q","region":"South West"},{"loc":[51.34582,-2.956202],"id":"INCD-46109-q","region":"South West"},{"loc":[50.69836,-2.721247],"id":"INCD-19834-s","region":"South West"},{"loc":[51.1469,-2.510274],"id":"INCD-46127-q","region":"South West"},{"loc":[50.44337,-4.11103],"id":"INCD-46033-q","region":"South West"},{"loc":[50.03838,-5.12202],"id":"INCD-19937-v","region":"South West"},{"loc":[50.2653,-5.242297],"id":"INCD-19940-v","region":"South West"},{"loc":[50.99135,-3.24772],"id":"INCD-46096-q","region":"South West"},{"loc":[50.28487,-3.779834],"id":"INCD-46119-q","region":"South West"},{"loc":[51.45261,-2.76357],"id":"INCD-46086-q","region":"South West"},{"loc":[51.27168,-2.565353],"id":"INCD-46113-q","region":"South West"},{"loc":[50.2595,-5.293207],"id":"INCD-20005-v","region":"South West"},{"loc":[51.0927,-3.24035],"id":"INCD-19821-s","region":"South West"},{"loc":[51.64485,-3.90614],"id":"INCD-27045-h","region":"South Wales"},{"loc":[51.60661,-4.176463],"id":"INCD-28464-g","region":"South Wales"},{"loc":[51.7154,-2.91941],"id":"INCD-28472-g","region":"South Wales"},{"loc":[51.6665,-3.196447],"id":"INCD-27062-h","region":"South Wales"},{"loc":[51.85098,-4.26152],"id":"INCD-28474-g","region":"South Wales"},{"loc":[51.60661,-4.176463],"id":"INCD-28465-g","region":"South Wales"},{"loc":[51.95779,-3.897453],"id":"INCD-27054-h","region":"South Wales"},{"loc":[51.90956,-2.728878],"id":"INCD-35718-b","region":"West Midlands"},{"loc":[52.93299,-2.254242],"id":"INCD-35723-b","region":"West Midlands"},{"loc":[52.39282,-2.2241],"id":"INCD-35725-b","region":"West Midlands"},{"loc":[51.75434,-2.561802],"id":"INCD-35739-b","region":"West Midlands"},{"loc":[52.20153,-1.71027],"id":"INCD-48827-c","region":"West Midlands"},{"loc":[51.91754,-2.038192],"id":"INCD-48818-c","region":"West Midlands"},{"loc":[52.66609,-2.37323],"id":"INCD-35726-b","region":"West Midlands"},{"loc":[51.52786,-2.430772],"id":"INCD-48809-c","region":"West Midlands"},{"loc":[52.4984,-1.92087],"id":"INCD-35717-b","region":"West Midlands"},{"loc":[52.79272,-1.938356],"id":"INCD-35731-b","region":"West Midlands"},{"loc":[52.38503,-1.748391],"id":"INCD-35707-b","region":"West Midlands"},{"loc":[52.4208,-2.512007],"id":"INCD-48830-c","region":"West Midlands"},{"loc":[52.45538,-2.045546],"id":"INCD-48700-c","region":"West Midlands"},{"loc":[52.51338,-2.04319],"id":"INCD-35689-b","region":"West Midlands"},{"loc":[53.03896,-0.591355],"id":"INCD-63282-m","region":"East Midlands"},{"loc":[52.33693,-1.58468],"id":"INCD-63301-m","region":"East Midlands"},{"loc":[53.3718,-0.882549],"id":"INCD-63273-m","region":"East Midlands"},{"loc":[52.83433,-1.17457],"id":"INCD-63292-m","region":"East Midlands"},{"loc":[52.7733,-0.142805],"id":"INCD-63303-m","region":"East Midlands"},{"loc":[52.90641,-1.398535],"id":"INCD-63295-m","region":"East Midlands"},{"loc":[53.1235,-1.1717],"id":"INCD-63236-m","region":"East Midlands"},{"loc":[52.94878,-0.945542],"id":"INCD-63281-m","region":"East Midlands"}],"updatePeriod":60000,"incidentStatus":200,"alertSummary":[{"id":26,"published":"Jul 4, 2022, 8:39:07 AM","flagAsNew":true,"isDefault":false}]}