{"lastUpdated":"2023-09-18T11:32:00.000+0100","twitterEnabled":0,"incidents":[{"loc":[50.85477,-3.951312],"id":"INCD-2959-t","region":"South West"},{"loc":[50.81046,-3.745688],"id":"INCD-2954-t","region":"South West"},{"loc":[51.15108,-4.177518],"id":"INCD-8606-l","region":"South West"},{"loc":[51.35201,-2.927826],"id":"INCD-8598-l","region":"South West"},{"loc":[51.00552,-3.120036],"id":"INCD-8603-l","region":"South West"},{"loc":[50.7019,-3.246902],"id":"INCD-8605-l","region":"South West"},{"loc":[50.92905,-3.355864],"id":"INCD-2971-t","region":"South West"},{"loc":[51.18041,-3.217581],"id":"INCD-2963-t","region":"South West"},{"loc":[50.8011,-3.45379],"id":"INCD-8583-l","region":"South West"},{"loc":[50.20836,-5.125201],"id":"INCD-8595-l","region":"South West"},{"loc":[50.74488,-3.964854],"id":"INCD-2966-t","region":"South West"},{"loc":[51.12756,-2.973794],"id":"INCD-8589-l","region":"South West"},{"loc":[50.71904,-3.553632],"id":"INCD-2975-t","region":"South West"},{"loc":[51.12477,-2.986167],"id":"INCD-2976-t","region":"South West"},{"loc":[50.73507,-3.681336],"id":"INCD-2970-t","region":"South West"},{"loc":[51.78126,-3.755704],"id":"INCD-5328-f","region":"South Wales"},{"loc":[52.9569,-2.105066],"id":"INCD-7173-p","region":"West Midlands"},{"loc":[52.52028,-2.416838],"id":"INCD-7175-p","region":"West Midlands"},{"loc":[51.764,-2.037352],"id":"INCD-7174-p","region":"West Midlands"},{"loc":[52.84077,-1.337756],"id":"INCD-15743-h","region":"East Midlands"},{"loc":[52.9979,-0.409288],"id":"INCD-15746-h","region":"East Midlands"},{"loc":[52.48862,-1.116211],"id":"INCD-15764-h","region":"East Midlands"},{"loc":[53.0392,-1.375884],"id":"INCD-15676-h","region":"East Midlands"},{"loc":[52.43343,-1.302707],"id":"INCD-15784-h","region":"East Midlands"},{"loc":[52.81188,-0.676616],"id":"INCD-15738-h","region":"East Midlands"},{"loc":[52.867,-1.203699],"id":"INCD-15751-h","region":"East Midlands"},{"loc":[52.76583,-0.384411],"id":"INCD-15728-h","region":"East Midlands"}],"updatePeriod":60000,"incidentStatus":200,"alertSummary":[{"id":6,"published":"Mar 15, 2021, 8:00:00 AM","flagAsNew":false,"isDefault":true}]}