{"lastUpdated":"2024-01-01T04:07:00.000+0000","twitterEnabled":0,"incidents":[{"loc":[51.3444,-2.445259],"id":"INCD-15001-l","region":"South West"},{"loc":[50.37527,-4.936196],"id":"INCD-15007-l","region":"South West"},{"loc":[51.20247,-2.988384],"id":"INCD-15003-l","region":"South West"},{"loc":[51.5102,-3.209004],"id":"INCD-8851-f","region":"South Wales"},{"loc":[52.15241,-0.891257],"id":"INCD-29456-h","region":"East Midlands"}],"updatePeriod":60000,"incidentStatus":200,"alertSummary":[{"id":6,"published":"Mar 15, 2021, 8:00:00 AM","flagAsNew":false,"isDefault":true}]}