{"lastUpdated":"2024-01-06T02:36:00.000+0000","twitterEnabled":0,"incidents":[{"loc":[50.09595,-5.273888],"id":"INCD-15458-l","region":"South West"},{"loc":[51.10934,-2.932113],"id":"INCD-15471-l","region":"South West"},{"loc":[51.48795,-3.140189],"id":"INCD-9029-f","region":"South Wales"},{"loc":[51.7521,-4.226455],"id":"INCD-9030-f","region":"South Wales"},{"loc":[52.55793,-0.630694],"id":"INCD-30244-h","region":"East Midlands"},{"loc":[52.53733,-1.373511],"id":"INCD-30222-h","region":"East Midlands"},{"loc":[53.15584,-1.199808],"id":"INCD-29843-h","region":"East Midlands"},{"loc":[52.53914,-1.37674],"id":"INCD-30197-h","region":"East Midlands"},{"loc":[52.92591,-1.279203],"id":"INCD-30247-h","region":"East Midlands"}],"updatePeriod":60000,"incidentStatus":200,"alertSummary":[{"id":6,"published":"Mar 15, 2021, 8:00:00 AM","flagAsNew":false,"isDefault":true}]}