{"lastUpdated":"2023-06-22T19:31:00.000+0100","twitterEnabled":0,"incidents":[{"loc":[50.99219,-3.00524],"id":"INCD-927-t","region":"South West"},{"loc":[50.82446,-4.530591],"id":"INCD-923-t","region":"South West"},{"loc":[51.04146,-2.924203],"id":"INCD-2568-l","region":"South West"},{"loc":[50.3888,-3.905145],"id":"INCD-2567-l","region":"South West"},{"loc":[50.3888,-3.905145],"id":"INCD-2572-l","region":"South West"},{"loc":[51.93025,-2.401036],"id":"INCD-1742-p","region":"West Midlands"},{"loc":[52.80669,-2.115472],"id":"INCD-1743-p","region":"West Midlands"},{"loc":[52.54434,-2.49137],"id":"INCD-1751-p","region":"West Midlands"},{"loc":[52.56808,-1.945118],"id":"INCD-1528-m","region":"West Midlands"},{"loc":[53.19597,-1.90825],"id":"INCD-1550-m","region":"West Midlands"},{"loc":[52.9797,-2.135206],"id":"INCD-1727-p","region":"West Midlands"},{"loc":[52.82641,-2.018761],"id":"INCD-1512-m","region":"West Midlands"},{"loc":[52.4392,-1.784594],"id":"INCD-1526-m","region":"West Midlands"},{"loc":[52.38027,-1.537176],"id":"INCD-4514-h","region":"East Midlands"},{"loc":[52.61226,-1.124122],"id":"INCD-5523-h","region":"East Midlands"},{"loc":[52.41463,-1.572735],"id":"INCD-5524-h","region":"East Midlands"},{"loc":[52.60095,-1.66744],"id":"INCD-5518-h","region":"East Midlands"},{"loc":[52.63721,-1.101368],"id":"INCD-5512-h","region":"East Midlands"},{"loc":[53.1997,-1.392747],"id":"INCD-5483-h","region":"East Midlands"},{"loc":[52.60662,-1.098688],"id":"INCD-5520-h","region":"East Midlands"},{"loc":[53.11014,-1.44982],"id":"INCD-5435-h","region":"East Midlands"},{"loc":[52.62647,-1.111576],"id":"INCD-5530-h","region":"East Midlands"},{"loc":[53.14891,-1.170272],"id":"INCD-5503-h","region":"East Midlands"},{"loc":[52.59738,-1.080052],"id":"INCD-5511-h","region":"East Midlands"},{"loc":[52.62632,-1.11768],"id":"INCD-5519-h","region":"East Midlands"},{"loc":[52.29956,-1.758363],"id":"INCD-5490-h","region":"East Midlands"},{"loc":[53.21517,-1.782],"id":"INCD-5459-h","region":"East Midlands"}],"updatePeriod":60000,"incidentStatus":200,"alertSummary":[{"id":6,"published":"Mar 15, 2021, 8:00:00 AM","flagAsNew":false,"isDefault":true}]}