{"lastUpdated":"2023-05-10T03:40:00.000+0100","twitterEnabled":0,"incidents":[{"loc":[50.73691,-2.761604],"id":"INCD-47677-q","region":"South West"},{"loc":[50.23611,-4.80132],"id":"INCD-47634-q","region":"South West"},{"loc":[52.67668,-1.852529],"id":"INCD-37024-b","region":"West Midlands"},{"loc":[51.92869,-2.380385],"id":"INCD-37079-b","region":"West Midlands"},{"loc":[52.59319,-1.12927],"id":"INCD-436-h","region":"East Midlands"},{"loc":[52.27667,-1.695508],"id":"INCD-422-h","region":"East Midlands"},{"loc":[53.02296,-1.480627],"id":"INCD-273-h","region":"East Midlands"}],"updatePeriod":60000,"incidentStatus":200,"alertSummary":[{"id":26,"published":"Jul 4, 2022, 8:39:07 AM","flagAsNew":true,"isDefault":false}]}