{"lastUpdated":"2023-06-27T10:04:00.000+0100","twitterEnabled":0,"incidents":[{"loc":[51.48232,-2.525027],"id":"INCD-649-u","region":"South West"},{"loc":[50.5284,-3.595825],"id":"INCD-2871-l","region":"South West"},{"loc":[50.112,-5.551563],"id":"INCD-21979-v","region":"South West"},{"loc":[50.76836,-3.359323],"id":"INCD-2870-l","region":"South West"},{"loc":[51.3509,-2.91679],"id":"INCD-2874-l","region":"South West"},{"loc":[51.94327,-3.389773],"id":"INCD-2432-f","region":"South Wales"},{"loc":[51.74958,-2.29573],"id":"INCD-2039-p","region":"West Midlands"},{"loc":[53.10913,-1.385089],"id":"INCD-5770-h","region":"East Midlands"},{"loc":[52.67538,-1.190954],"id":"INCD-6002-h","region":"East Midlands"},{"loc":[52.273,-1.39061],"id":"INCD-6027-h","region":"East Midlands"},{"loc":[52.57779,-1.101994],"id":"INCD-6037-h","region":"East Midlands"}],"updatePeriod":60000,"incidentStatus":200,"alertSummary":[{"id":6,"published":"Mar 15, 2021, 8:00:00 AM","flagAsNew":false,"isDefault":true}]}