{"lastUpdated":"2023-07-26T20:01:00.000+0100","twitterEnabled":0,"incidents":[{"loc":[50.1923,-5.42888],"id":"INCD-4907-l","region":"South West"},{"loc":[50.71157,-3.516402],"id":"INCD-4910-l","region":"South West"},{"loc":[50.23509,-3.782129],"id":"INCD-4915-l","region":"South West"},{"loc":[51.01205,-4.178682],"id":"INCD-4920-l","region":"South West"},{"loc":[51.61269,-2.973181],"id":"INCD-582-j","region":"South Wales"},{"loc":[52.52581,-1.784938],"id":"INCD-3748-m","region":"West Midlands"},{"loc":[51.67948,-2.223059],"id":"INCD-4215-p","region":"West Midlands"},{"loc":[52.642,-2.09754],"id":"INCD-3759-m","region":"West Midlands"},{"loc":[52.18755,-2.518026],"id":"INCD-4214-p","region":"West Midlands"},{"loc":[52.10234,-1.78292],"id":"INCD-3728-m","region":"West Midlands"},{"loc":[52.72166,-1.138678],"id":"INCD-9910-h","region":"East Midlands"},{"loc":[52.38585,-1.264843],"id":"INCD-9960-h","region":"East Midlands"},{"loc":[53.1021,-1.565017],"id":"INCD-9934-h","region":"East Midlands"},{"loc":[52.37451,-0.720723],"id":"INCD-9924-h","region":"East Midlands"},{"loc":[52.63912,-1.69189],"id":"INCD-9959-h","region":"East Midlands"},{"loc":[52.9338,-1.492019],"id":"INCD-9898-h","region":"East Midlands"},{"loc":[52.71541,-1.351942],"id":"INCD-9860-h","region":"East Midlands"}],"updatePeriod":60000,"incidentStatus":200,"alertSummary":[{"id":6,"published":"Mar 15, 2021, 8:00:00 AM","flagAsNew":false,"isDefault":true}]}