{"lastUpdated":"2023-06-05T10:30:00.000+0100","twitterEnabled":0,"incidents":[{"loc":[50.4221,-4.893755],"id":"INCD-21339-v","region":"South West"},{"loc":[51.4803,-2.589286],"id":"INCD-277-u","region":"South West"},{"loc":[51.44271,-2.790684],"id":"INCD-283-u","region":"South West"},{"loc":[50.45808,-4.460212],"id":"INCD-1242-l","region":"South West"},{"loc":[50.57536,-3.478014],"id":"INCD-21346-v","region":"South West"},{"loc":[50.89875,-3.486497],"id":"INCD-1234-l","region":"South West"},{"loc":[51.482,-2.586837],"id":"INCD-280-u","region":"South West"},{"loc":[50.87489,-2.794963],"id":"INCD-1243-l","region":"South West"},{"loc":[50.98334,-4.404792],"id":"INCD-1256-l","region":"South West"},{"loc":[51.5365,-3.367151],"id":"INCD-1094-e","region":"South Wales"},{"loc":[51.74323,-3.266157],"id":"INCD-1623-f","region":"South Wales"},{"loc":[52.22982,-2.749678],"id":"INCD-68-p","region":"West Midlands"},{"loc":[52.37163,-2.24926],"id":"INCD-73-p","region":"West Midlands"},{"loc":[53.32633,-0.939622],"id":"INCD-3003-h","region":"East Midlands"},{"loc":[52.92385,-1.51583],"id":"INCD-3024-h","region":"East Midlands"},{"loc":[52.6032,-1.065534],"id":"INCD-3009-h","region":"East Midlands"},{"loc":[51.99233,-0.73824],"id":"INCD-3026-h","region":"East Midlands"},{"loc":[52.95534,-1.17474],"id":"INCD-3038-h","region":"East Midlands"}],"updatePeriod":60000,"incidentStatus":200,"alertSummary":[{"id":26,"published":"Jul 4, 2022, 8:39:07 AM","flagAsNew":true,"isDefault":false}]}