{"lastUpdated":"2024-04-18T11:04:00.000+0100","twitterEnabled":0,"incidents":[{"loc":[51.40947,-2.627554],"id":"INCD-5427-u","region":"South West"},{"loc":[51.3181,-2.836395],"id":"INCD-21241-l","region":"South West"},{"loc":[50.72009,-3.542815],"id":"INCD-20303-l","region":"South West"},{"loc":[51.46679,-2.821952],"id":"INCD-5428-u","region":"South West"},{"loc":[51.74352,-3.540719],"id":"INCD-2290-j","region":"South Wales"},{"loc":[51.64935,-4.015002],"id":"INCD-12811-f","region":"South Wales"},{"loc":[51.80073,-3.935522],"id":"INCD-12928-f","region":"South Wales"},{"loc":[51.5827,-2.991359],"id":"INCD-2371-j","region":"South Wales"},{"loc":[51.50022,-3.534573],"id":"INCD-12935-f","region":"South Wales"},{"loc":[51.50022,-3.534573],"id":"INCD-12932-f","region":"South Wales"},{"loc":[51.44362,-3.177762],"id":"INCD-12925-f","region":"South Wales"},{"loc":[52.56031,-1.975957],"id":"INCD-21495-p","region":"West Midlands"},{"loc":[52.59929,-2.104855],"id":"INCD-21451-p","region":"West Midlands"},{"loc":[52.43116,-1.69203],"id":"INCD-21506-p","region":"West Midlands"},{"loc":[53.01052,-2.180655],"id":"INCD-21496-p","region":"West Midlands"},{"loc":[52.75179,-1.246892],"id":"INCD-42019-h","region":"East Midlands"}],"updatePeriod":60000,"incidentStatus":200,"alertSummary":[{"id":6,"published":"Mar 15, 2021, 8:00:00 AM","flagAsNew":false,"isDefault":true}]}