{"lastUpdated":"2023-02-22T17:31:00.000+0000","twitterEnabled":0,"incidents":[{"loc":[50.40784,-5.08546],"id":"INCD-18624-v","region":"South West"},{"loc":[51.36883,-2.35172],"id":"INCD-12107-r","region":"South West"},{"loc":[50.3568,-4.117516],"id":"INCD-43558-q","region":"South West"},{"loc":[51.22998,-3.826604],"id":"INCD-18727-s","region":"South West"},{"loc":[51.456,-2.582272],"id":"INCD-12095-r","region":"South West"},{"loc":[51.40513,-2.317078],"id":"INCD-12104-r","region":"South West"},{"loc":[51.5816,-2.84472],"id":"INCD-26905-g","region":"South Wales"},{"loc":[51.67831,-4.737005],"id":"INCD-26916-g","region":"South Wales"},{"loc":[51.6567,-3.89053],"id":"INCD-25421-h","region":"South Wales"},{"loc":[52.51725,-2.127044],"id":"INCD-1864-l","region":"West Midlands"},{"loc":[52.77,-1.950542],"id":"INCD-33174-b","region":"West Midlands"},{"loc":[52.59329,-1.83381],"id":"INCD-1868-l","region":"West Midlands"},{"loc":[52.49552,-1.828698],"id":"INCD-45644-c","region":"West Midlands"},{"loc":[52.93191,-1.130806],"id":"INCD-57760-m","region":"East Midlands"},{"loc":[53.03174,-0.525781],"id":"INCD-57829-m","region":"East Midlands"},{"loc":[52.89302,-1.156868],"id":"INCD-57807-m","region":"East Midlands"},{"loc":[52.88827,-1.451027],"id":"INCD-57825-m","region":"East Midlands"}],"updatePeriod":60000,"incidentStatus":200,"alertSummary":[{"id":26,"published":"Jul 4, 2022, 8:39:07 AM","flagAsNew":true,"isDefault":false}]}