{"lastUpdated":"2023-07-15T19:06:00.000+0100","twitterEnabled":0,"incidents":[{"loc":[50.74444,-3.520624],"id":"INCD-4211-l","region":"South West"},{"loc":[50.67367,-3.493272],"id":"INCD-4165-l","region":"South West"},{"loc":[50.47361,-3.511705],"id":"INCD-4181-l","region":"South West"},{"loc":[50.15004,-5.090649],"id":"INCD-4103-l","region":"South West"},{"loc":[51.02914,-4.122407],"id":"INCD-4186-l","region":"South West"},{"loc":[50.94988,-3.127239],"id":"INCD-4149-l","region":"South West"},{"loc":[50.8353,-3.865144],"id":"INCD-4201-l","region":"South West"},{"loc":[50.44019,-3.777219],"id":"INCD-4185-l","region":"South West"},{"loc":[50.85617,-3.216474],"id":"INCD-4191-l","region":"South West"},{"loc":[50.5236,-3.606456],"id":"INCD-4205-l","region":"South West"},{"loc":[50.28038,-5.124935],"id":"INCD-4213-l","region":"South West"},{"loc":[50.3473,-4.779735],"id":"INCD-4187-l","region":"South West"},{"loc":[51.07725,-4.051442],"id":"INCD-4190-l","region":"South West"},{"loc":[51.60316,-2.351594],"id":"INCD-3120-m","region":"West Midlands"},{"loc":[51.78427,-2.189365],"id":"INCD-3168-m","region":"West Midlands"},{"loc":[51.62102,-2.57217],"id":"INCD-3098-m","region":"West Midlands"},{"loc":[52.2836,-2.29221],"id":"INCD-3135-m","region":"West Midlands"},{"loc":[52.2648,-2.988088],"id":"INCD-3000-m","region":"West Midlands"},{"loc":[52.82898,-2.306264],"id":"INCD-3151-m","region":"West Midlands"},{"loc":[52.40327,-1.858026],"id":"INCD-3017-m","region":"West Midlands"},{"loc":[51.88781,-2.396168],"id":"INCD-3100-m","region":"West Midlands"},{"loc":[52.43583,-1.953915],"id":"INCD-3396-p","region":"West Midlands"},{"loc":[52.53286,-2.784211],"id":"INCD-3138-m","region":"West Midlands"},{"loc":[53.09151,-2.210232],"id":"INCD-3139-m","region":"West Midlands"},{"loc":[52.32287,-1.819799],"id":"INCD-3418-p","region":"West Midlands"},{"loc":[51.9801,-2.353171],"id":"INCD-3152-m","region":"West Midlands"},{"loc":[51.854,-2.558382],"id":"INCD-3165-m","region":"West Midlands"},{"loc":[52.09046,-1.982177],"id":"INCD-348995-f","region":"West Midlands"},{"loc":[52.19065,-2.66938],"id":"INCD-3144-m","region":"West Midlands"},{"loc":[52.91086,-2.107066],"id":"INCD-3148-m","region":"West Midlands"},{"loc":[51.70099,-2.61863],"id":"INCD-3132-m","region":"West Midlands"},{"loc":[52.68918,-1.926932],"id":"INCD-3088-m","region":"West Midlands"},{"loc":[52.21492,-2.08489],"id":"INCD-3124-m","region":"West Midlands"},{"loc":[52.4773,-1.980257],"id":"INCD-3392-p","region":"West Midlands"},{"loc":[51.80649,-2.461881],"id":"INCD-3145-m","region":"West Midlands"},{"loc":[52.0715,-1.902862],"id":"INCD-3080-m","region":"West Midlands"},{"loc":[51.75919,-2.488723],"id":"INCD-3108-m","region":"West Midlands"},{"loc":[52.72011,-2.739242],"id":"INCD-3131-m","region":"West Midlands"},{"loc":[52.04495,-1.55464],"id":"INCD-3147-m","region":"West Midlands"},{"loc":[52.69799,-1.817758],"id":"INCD-3167-m","region":"West Midlands"},{"loc":[52.68336,-0.16396],"id":"INCD-8549-h","region":"East Midlands"},{"loc":[52.56314,-1.366992],"id":"INCD-8554-h","region":"East Midlands"},{"loc":[53.21155,-1.854641],"id":"INCD-8603-h","region":"East Midlands"},{"loc":[53.16285,-1.409361],"id":"INCD-8588-h","region":"East Midlands"},{"loc":[53.233,-1.444962],"id":"INCD-8599-h","region":"East Midlands"},{"loc":[52.26427,-0.900646],"id":"INCD-8609-h","region":"East Midlands"},{"loc":[52.90641,-1.398535],"id":"INCD-8593-h","region":"East Midlands"},{"loc":[53.27612,-1.797256],"id":"INCD-8511-h","region":"East Midlands"},{"loc":[52.62553,-1.11483],"id":"INCD-8605-h","region":"East Midlands"},{"loc":[53.17235,-0.538216],"id":"INCD-8556-h","region":"East Midlands"}],"updatePeriod":60000,"incidentStatus":200,"alertSummary":[{"id":8,"published":"Jul 14, 2023, 2:30:00 PM","flagAsNew":true,"isDefault":false}]}