{"lastUpdated":"2023-01-18T00:24:00.000+0000","incidents":[{"loc":[50.73883,-3.070521],"id":"INCD-41968-q","region":"SWE"},{"loc":[50.35029,-3.586613],"id":"INCD-41961-q","region":"SWE"},{"loc":[50.70058,-3.521216],"id":"INCD-41958-q","region":"SWE"},{"loc":[52.58463,-2.259186],"id":"INCD-43353-c","region":"WM"},{"loc":[52.19283,-2.225389],"id":"INCD-43368-c","region":"WM"},{"loc":[52.4315,-1.79456],"id":"INCD-43320-c","region":"WM"}],"updatePeriod":120000,"incidentStatus":200,"alertSummary":[{"id":26,"published":"Jul 4, 2022, 8:39:07 AM","flagAsNew":true,"isDefault":false}]}