{"lastUpdated":"2023-01-30T18:06:00.000+0000","incidents":[{"loc":[51.516,-2.608034],"id":"INCD-42545-q","region":"South West"},{"loc":[50.28551,-4.799774],"id":"INCD-42536-q","region":"South West"},{"loc":[51.1588,-2.706641],"id":"INCD-18246-s","region":"South West"},{"loc":[50.38021,-4.02728],"id":"INCD-42538-q","region":"South West"},{"loc":[50.40609,-4.09196],"id":"INCD-18067-v","region":"South West"},{"loc":[51.14534,-2.723648],"id":"INCD-18273-s","region":"South West"},{"loc":[50.62658,-4.713431],"id":"INCD-42547-q","region":"South West"},{"loc":[52.19769,-2.218361],"id":"INCD-44144-c","region":"West Midlands"},{"loc":[52.97096,-0.025326],"id":"INCD-55546-m","region":"East Midlands"},{"loc":[52.51552,-1.51034],"id":"INCD-55481-m","region":"East Midlands"},{"loc":[53.31845,-1.105021],"id":"INCD-55501-m","region":"East Midlands"},{"loc":[52.89977,-0.622173],"id":"INCD-55462-m","region":"East Midlands"},{"loc":[52.63182,-1.130528],"id":"INCD-55543-m","region":"East Midlands"}],"updatePeriod":60000,"incidentStatus":200,"alertSummary":[{"id":26,"published":"Jul 4, 2022, 8:39:07 AM","flagAsNew":true,"isDefault":false}]}